cplist.cpython-37m-darwin.so
python_cplist-0.2.dist-info/LICENSE
python_cplist-0.2.dist-info/METADATA
python_cplist-0.2.dist-info/WHEEL
python_cplist-0.2.dist-info/top_level.txt
python_cplist-0.2.dist-info/RECORD
