Metadata-Version: 2.1
Name: python-cplist
Version: 0.2
Summary: CPython property list parser
Home-page: UNKNOWN
Author: Jonathan Goren
Author-email: jonagn@gmail.com
License: UNKNOWN
Platform: UNKNOWN
